cli/__init__.py
cli/cli.py
cli/command_index.py
cli/commands/__init__.py
cli/commands/chat.py
cli/commands/config.py
cli/commands/edit.py
cli/commands/grab.py
cli/commands/history.py
cli/commands/plan.py
cli/commands/pr.py
cli/commands/run.py
cli/commands/task.py
cli/commands/upgrade.py
cli/constants.py
cli/detect_repository.py
cli/models.py
cli/plan_executor.py
cli/prompt_template.py
cli/skill_index.py
cli/status_indicator.py
cli/task_handler.py
cli/task_runner.py
cli/user_config.py
cli/util.py
pr_pilot_cli-1.20.2.dist-info/LICENSE
pr_pilot_cli-1.20.2.dist-info/METADATA
pr_pilot_cli-1.20.2.dist-info/WHEEL
pr_pilot_cli-1.20.2.dist-info/entry_points.txt
pr_pilot_cli-1.20.2.dist-info/RECORD
