Metadata-Version: 2.1
Name: pr-pilot-cli
Version: 1.20.2
Summary: CLI for PR Pilot, a text-to-task automation platform.
Home-page: https://www.pr-pilot.ai
License: GPL-3.0
Author: Marco Lamina
Author-email: marco@arcane.engineer
Requires-Python: >=3.10.0,<3.11.0
Classifier: License :: OSI Approved :: GNU General Public License v3 (GPLv3)
Classifier: Programming Language :: Python :: 3
Classifier: Programming Language :: Python :: 3.10
Requires-Dist: arcane-engine (==1.9.1)
Requires-Dist: click (==8.1.7)
Requires-Dist: humanize (>=4.9.0,<5.0.0)
Requires-Dist: inquirer (>=3.2.5,<4.0.0)
Requires-Dist: jinja2 (==3.1.4)
Requires-Dist: pyyaml (==6.0.1)
Requires-Dist: rich (==13.7.1)
Requires-Dist: websockets (>=12.0,<13.0)
Requires-Dist: yaspin (==3.0.2)
Project-URL: Documentation, https://docs.pr-pilot.ai
Project-URL: Repository, https://github.com/arc-eng/cli
